evnhcm/__init__.py
evnhcm/app.py
evnhcm-0.0.3.dist-info/METADATA
evnhcm-0.0.3.dist-info/WHEEL
evnhcm-0.0.3.dist-info/top_level.txt
evnhcm-0.0.3.dist-info/RECORD
