Metadata-Version: 2.1
Name: evnhcm
Version: 0.0.3
Summary: Lấy thông tin điện lực HCM
Home-page: UNKNOWN
Author: Xuong Huynh
Author-email: longxuongz@gmail.com
License: MIT
Keywords: evn,hcm,evnhcm
Platform: UNKNOWN
Classifier: Development Status :: 3 - Alpha
Classifier: Intended Audience :: Developers
Classifier: Topic :: Software Development :: Build Tools
Classifier: License :: OSI Approved :: MIT License
Classifier: Programming Language :: Python :: 3
Classifier: Programming Language :: Python :: 3.4
Classifier: Programming Language :: Python :: 3.5
Classifier: Programming Language :: Python :: 3.6
